mbb/__init__.py
mbb/mbb.py
mbb/mbb_funcs.py
mbb-0.5.0.dist-info/licenses/LICENSE
mbb-0.5.0.dist-info/METADATA
mbb-0.5.0.dist-info/WHEEL
mbb-0.5.0.dist-info/top_level.txt
mbb-0.5.0.dist-info/RECORD
