Metadata-Version: 2.4
Name: mbb
Version: 0.5.0
License-File: LICENSE
Requires-Dist: matplotlib
Requires-Dist: astropy
Requires-Dist: numpy
Requires-Dist: scipy
Requires-Dist: emcee
Requires-Dist: corner
Requires-Dist: tqdm
Dynamic: license-file
